boxd-client/__init__.py
boxd-client/binary.py
boxd-client/boxd_client.py
boxd-client/hash.py
boxd-client/keystore.py
boxd-client/op_code.py
boxd-client/signutils.py
boxd-client/utils.py
boxd-client/proto/__init__.py
boxd-client/proto/block_pb2.py
boxd-client/proto/block_pb2_grpc.py
boxd-client/proto/common_pb2.py
boxd-client/proto/common_pb2_grpc.py
boxd-client/proto/control_pb2.py
boxd-client/proto/control_pb2_grpc.py
boxd-client/proto/db_pb2.py
boxd-client/proto/db_pb2_grpc.py
boxd-client/proto/faucet_pb2.py
boxd-client/proto/faucet_pb2_grpc.py
boxd-client/proto/transaction_pb2.py
boxd-client/proto/transaction_pb2_grpc.py
boxd-client/proto/web_pb2.py
boxd-client/proto/web_pb2_grpc.py
boxd-unpack-python/__init__.py
boxd-unpack-python/binary.py
boxd-unpack-python/boxd_client.py
boxd-unpack-python/hash.py
boxd-unpack-python/keystore.py
boxd-unpack-python/op_code.py
boxd-unpack-python/signutils.py
boxd-unpack-python/utils.py
boxd-unpack-python/proto/__init__.py
boxd-unpack-python/proto/block_pb2.py
boxd-unpack-python/proto/block_pb2_grpc.py
boxd-unpack-python/proto/common_pb2.py
boxd-unpack-python/proto/common_pb2_grpc.py
boxd-unpack-python/proto/control_pb2.py
boxd-unpack-python/proto/control_pb2_grpc.py
boxd-unpack-python/proto/db_pb2.py
boxd-unpack-python/proto/db_pb2_grpc.py
boxd-unpack-python/proto/faucet_pb2.py
boxd-unpack-python/proto/faucet_pb2_grpc.py
boxd-unpack-python/proto/transaction_pb2.py
boxd-unpack-python/proto/transaction_pb2_grpc.py
boxd-unpack-python/proto/web_pb2.py
boxd-unpack-python/proto/web_pb2_grpc.py
boxd_client/__init__.py
boxd_client/binary.py
boxd_client/boxd_client.py
boxd_client/boxd_daemon.py
boxd_client/hash.py
boxd_client/keystore.py
boxd_client/op_code.py
boxd_client/signutils.py
boxd_client/utils.py
boxd_client/proto/__init__.py
boxd_client/proto/block_pb2.py
boxd_client/proto/block_pb2_grpc.py
boxd_client/proto/common_pb2.py
boxd_client/proto/common_pb2_grpc.py
boxd_client-0.2.0.dist-info/METADATA
boxd_client-0.2.0.dist-info/RECORD
boxd_client-0.2.0.dist-info/WHEEL
boxd_client-0.2.0.dist-info/top_level.txt
